ifcfactory/__init__.py
ifcfactory/_internal/__init__.py
ifcfactory/_internal/material_base.py
ifcfactory/_internal/primitives_base.py
ifcfactory/_internal/pset_base.py
ifcfactory/_internal/unit_base.py
ifcfactory/element.py
ifcfactory/operations.py
ifcfactory/primitives.py
ifcfactory-0.2.2.dist-info/METADATA
ifcfactory-0.2.2.dist-info/WHEEL
ifcfactory-0.2.2.dist-info/licenses/LICENSE
ifcfactory-0.2.2.dist-info/RECORD
