Metadata-Version: 2.4
Name: ifcfactory
Version: 0.2.2
Summary: A modular geometry system for creating BIM elements with composable geometry creation
License: LGPL-2.1
License-File: LICENSE
Keywords: BIM,IFC,geometry,ifcopenshell,construction
Author: Ahmed Salem
Author-email: ahmed.salem@gv.hamburg.de
Requires-Python: >=3.11,<3.13
Classifier: Development Status :: 4 - Beta
Classifier: Intended Audience :: Developers
Classifier: Topic :: Scientific/Engineering :: GIS
Classifier: License :: OSI Approved :: GNU Lesser General Public License v2 (LGPLv2)
Classifier: Programming Language :: Python :: 3.11
Classifier: Programming Language :: Python :: 3.12
Requires-Dist: icosphere (>=0.1.3,<0.2.0)
Requires-Dist: ifc5d (>=0.8.4,<0.9.0)
Requires-Dist: ifcopenshell (==0.8.4)
Requires-Dist: pint (>=0.25.2,<0.26.0)
Requires-Dist: pydantic (>=2.12.5,<3.0.0)
Project-URL: Homepage, https://github.com/LGV-BIM-Leitstelle/ifcfactory
Project-URL: Issues, https://github.com/LGV-BIM-Leitstelle/ifcfactory/issues
Project-URL: Repository, https://github.com/LGV-BIM-Leitstelle/ifcfactory
